asjp/__init__.py
asjp/__version__.py
asjp/asjp.py
asjp/data/chart
asjp/tests/__init__.py
asjp/tests/test_asjp.py
asjp-0.0.2.dist-info/DESCRIPTION.rst
asjp-0.0.2.dist-info/METADATA
asjp-0.0.2.dist-info/RECORD
asjp-0.0.2.dist-info/WHEEL
asjp-0.0.2.dist-info/metadata.json
asjp-0.0.2.dist-info/top_level.txt
