Metadata-Version: 2.0
Name: asjp
Version: 0.0.2
Summary: ASJP conversion and tokenisation utils
Home-page: https://github.com/pavelsof/asjp
Author: Pavel Sofroniev
Author-email: pavelsof@gmail.com
License: MIT
Keywords: ASJP ASJPcode IPA
Platform: UNKNOWN
Classifier: Development Status :: 4 - Beta
Classifier: Intended Audience :: Developers
Classifier: Intended Audience :: Science/Research
Classifier: License :: OSI Approved :: MIT License
Classifier: Programming Language :: Python :: 3
Classifier: Topic :: Text Processing :: Linguistic
Requires-Python: >=3
Requires-Dist: ipatok (>=0.2)
